{
"type": "FeatureCollection",
                                                                                
"features": [
{ "type": "Feature", "properties": { "Name": "Parada Bonita", "Description": "<img width='256' src=\"\"><br> <b>Tipo:<\/b> Lanchonete <br><b>Endereço:<\/b> Joaquim Amantino Ferreira <br><b>Site:<\/b>  <br><b>Telefone:<\/b> (15) 3544-1353 (15) 9968-24542 <br><b>Email:<\/b> lauragbarao21@gmail.com <br><b>Pratos:<\/b> Refeições a la carte tipo comida comercial, Refeições com pratos típicos regionais, Snacks, lanches, porções, salgados, Café da manhã, Sobremesas <br><b>Oferece também:<\/b> Arroz com costelinha de porco, Arroz com suan, Arroz com frango, Cural de milho, Quirela de milho com costelinha de porco, Cural de milho com frango, Bolinho de frango, Paçoca de carne, Quirela com frango <br><b>Infra-estrutura:<\/b>  <br><b>Horário de funcionamento:<\/b>Café da manhã, Almoço, Refeições intermediárias (lanches, salgados, etc): das 8h - 21h <br><b>Nome do Responsável:<\/b> Sudenir de Araujo" }, "geometry": { "type": "Point", "coordinates": [ -48.366280564033843, -24.101798850506359, 0.0 ] } }
,
{ "type": "Feature", "properties": { "Name": "Sorveteria e Lanchonete Parof", "Description": "<img width='256' src=\"\"><br> <b>Tipo:<\/b> Restaurante, lanchonete, Sorveteria <br><b>Endereço:<\/b> Praça Bom Jesus, 51 <br><b>Site:<\/b>  <br><b>Telefone:<\/b> (15) 3544-1181 (15) 99761-9258 <br><b>Email:<\/b> sorveteria_parof@hotmail.com <br><b>Pratos:<\/b> Refeições com pratos típicos regionais, Snacks, lanches, porções, salgados, Café da manhã, Sobremesas <br><b>Oferece também:<\/b> Arroz com costelinha de porco, Arroz com suan, Arroz com frango, Cabeça de porco ensopada, Ensopado de ovo, a Jacuva, Cural de milho, Quirela de milho com costelinha de porco, Cural de milho com frango, Bolinho de frango, Virado de frango com melancia, Paçoca de carne, Quirela com frango, Biscoito de Polvilho com amendoim, Rojão <br><b>Infra-estrutura:<\/b>  <br><b>Horário de funcionamento:<\/b>Café da manhã, Almoço, Refeições intermediárias (lanches, salgados, etc): das 08:30 às 22:00 horas  <br><b>Nome do Responsável:<\/b> Matheus Brisolla" }, "geometry": { "type": "Point", "coordinates": [ -48.365402124764429, -24.098836465181769, 0.0 ] } }

]
}
