{
"type": "FeatureCollection",
                                                                                
"features": [
{ "type": "Feature", "properties": { "Name": "Parque Estadual Intervales", "Description": "<img width='256' src=\"http:\/\/www3.ambiente.sp.gov.br\/wp-content\/uploads\/hotsites\/Parque_Intervales\/3.jpg\"><br> <b>Tipo:<\/b> Pousada <br><b>Endereço:<\/b> Estrada Municipal Ribeirão Grande, km 25 <br><b>Site:<\/b> <a href=\"http:\/\/www3.ambiente.sp.gov.br\/parque-intervales\/\">http:\/\/www3.ambiente.sp.gov.br\/parque-intervales\/<\/a> <br><b>Facebook:<\/b> <a href=\"https:\/\/www.facebook.com\/brazilnature\/\">https:\/\/www.facebook.com\/brazilnature\/<\/a> <br><b>Telefone:<\/b> 015 3542-1511 <br><b>Email:<\/b> pe.intervales@fflroestal.sp.gov.br <br><b>Número de leitos:<\/b> 80 <br><b>Capacidade máxima de hospedagem:<\/b> 80 <br><b>Serviços:<\/b> Alojamento, Alimentação, Passeios, Lazer <br><b>Infra-estrutura:<\/b> Lençóis e toalhas <br><b>Horário de funcionamento:<\/b> segunda a segunda das 8:00 as 20:00 hs <br><b>Nome do Responsável:<\/b> Fundação Florestal" }, "geometry": { "type": "Point", "coordinates": [ -48.409358265566802, -24.267884903257059, 0.0 ] } }
,
{ "type": "Feature", "properties": { "Name": "Paraiso Eco Lodge", "Description": "<img width='256' src=\"http:\/\/brasilparaiso.com\/wp-content\/themes\/brasilparaiso2016\/imagens\/obs-de-aves\/gastronomia.jpg\"><br> <b>Tipo:<\/b> Pousada <br><b>Endereço:<\/b> Alameda do Museu s\/n  <br><b>Site:<\/b> <a href=\"http:\/\/www.brasilparaiso.com\/\">http:\/\/www.brasilparaiso.com\/<\/a> <br><b>Telefone:<\/b> 015 3542-4525 <br><b>Email:<\/b> contato@brasilparaiso.com <br><b>Número de leitos:<\/b> 22 <br><b>Capacidade máxima de hospedagem:<\/b> 55 <br><b>Serviços:<\/b> Alojamento, Alimentação, Passeios, Lazer <br><b>Infra-estrutura:<\/b> Wi-fi, Estacionamento, Ar-condicionado, Frigobar, Ventilador, Lençois e toalhas, Kit de higiene pessoal, Serviço de bar, Café da manhã incluso, Meios de locomoção <br><b>Horário de funcionamento:<\/b> Variável <br><b>Nome do Responsável:<\/b> Manoel Pereira Lizo Filho" }, "geometry": { "type": "Point", "coordinates": [ -48.382751545461737, -24.24377102555523, 0.0 ] } }
,
{ "type": "Feature", "properties": { "Name": "Paraíso Arte Hotel", "Description": "<img width='256' src=\"http:\/\/brasilparaiso.com\/wp-content\/themes\/brasilparaiso2016\/imagens\/obs-de-aves\/gastronomia.jpg\"><br> <b>Tipo:<\/b> Hotel <br><b>Endereço:<\/b> Fazenda Paraiso <br><b>Site:<\/b> <a href=\"http:\/\/www.paraisoartehotel.com\/\">http:\/\/www.paraisoartehotel.com\/<\/a> <br><b>Telefone:<\/b> 015 3542-4525 <br><b>Email:<\/b> contato@brasilparaiso.com <br><b>Número de leitos:<\/b> 23 <br><b>Capacidade máxima de hospedagem:<\/b> 110 <br><b>Serviços:<\/b> Alojamento, Alimentação, Passeios, Lazer, Cursos <br><b>Infra-estrutura:<\/b> Wi-fi, Estacionamento, Frigobar, Ventilador, Lençois e toalhas, Kit de higiene pessoal, Serviço de bar, Café da manhã incluso, Meios de locomoção <br><b>Horário de funcionamento:<\/b> Variável <br><b>Nome do Responsável:<\/b> Manoel Pereira Lizo Filho" }, "geometry": { "type": "Point", "coordinates": [ -48.382703991010452, -24.243851808351351, 0.0 ] } }

]
}
